{
  "indexes": [
    {
      "collectionGroup": "customers",
      "queryScope": "COLLECTION",
      "fields": [
        { "fieldPath": "isDeleted", "order": "ASCENDING" },
        { "fieldPath": "createdAt", "order": "DESCENDING" }
      ]
    },
    {
      "collectionGroup": "materials",
      "queryScope": "COLLECTION",
      "fields": [
        { "fieldPath": "isDeleted", "order": "ASCENDING" },
        { "fieldPath": "name", "order": "ASCENDING" }
      ]
    },
    {
      "collectionGroup": "payments",
      "queryScope": "COLLECTION",
      "fields": [
        { "fieldPath": "customerId", "order": "ASCENDING" },
        { "fieldPath": "createdAt", "order": "DESCENDING" }
      ]
    },
    {
      "collectionGroup": "payments",
      "queryScope": "COLLECTION",
      "fields": [
        { "fieldPath": "invoiceId", "order": "ASCENDING" },
        { "fieldPath": "createdAt", "order": "DESCENDING" }
      ]
    },
    {
      "collectionGroup": "invoices",
      "queryScope": "COLLECTION",
      "fields": [
        { "fieldPath": "customerId", "order": "ASCENDING" },
        { "fieldPath": "createdAt", "order": "DESCENDING" }
      ]
    }
  ],
  "fieldOverrides": []
}
